MANIFEST.in
setup.py
ate_master_app/LICENSE.txt
ate_master_app/README.md
ate_master_app/__init__.py
ate_master_app/launch_master.py
ate_master_app/master_application.py
ate_master_app/master_application_dev_mode.py
ate_master_app/master_connection_handler.py
ate_master_app/master_webservice.py
ate_master_app/peripheral_controller.py
ate_master_app/user_settings.py
ate_master_app/execution_strategy/__init__.py
ate_master_app/execution_strategy/execution_strategy.py
ate_master_app/parameter_parser/__init__.py
ate_master_app/parameter_parser/filesystem_data_source.py
ate_master_app/parameter_parser/parser_factory.py
ate_master_app/parameter_parser/static_data_source.py
ate_master_app/parameter_parser/xml_parameter_parser.py
ate_master_app/resulthandling/__init__.py
ate_master_app/resulthandling/result_collection_handler.py
ate_master_app/statemachines/MultiSite.py
ate_master_app/statemachines/TestingSiteMachine.py
ate_master_app/statemachines/TestsExecutionMachine.py
ate_master_app/statemachines/__init__.py
ate_master_app/task_handler/__init__.py
ate_master_app/task_handler/task_handler.py
ate_master_app/utils/__init__.py
ate_master_app/utils/bin_information.py
ate_master_app/utils/command_executor.py
ate_master_app/utils/master_configuration.py
ate_master_app/utils/part_information.py
ate_master_app/utils/result_Information_handler.py
ate_master_app/utils/site_information.py
ate_master_app/utils/table_information.py
ate_master_app/utils/yield_information.py
requirements/run.txt
semi_ate_master_app.egg-info/PKG-INFO
semi_ate_master_app.egg-info/SOURCES.txt
semi_ate_master_app.egg-info/dependency_links.txt
semi_ate_master_app.egg-info/entry_points.txt
semi_ate_master_app.egg-info/requires.txt
semi_ate_master_app.egg-info/top_level.txt